edf_fusion/__init__.py
edf_fusion/__version__.py
edf_fusion/client/__init__.py
edf_fusion/client/config.py
edf_fusion/client/impl.py
edf_fusion/client/api/__init__.py
edf_fusion/client/api/auth.py
edf_fusion/client/api/case.py
edf_fusion/client/api/constant.py
edf_fusion/client/api/download.py
edf_fusion/client/api/event.py
edf_fusion/client/api/info.py
edf_fusion/concept/__init__.py
edf_fusion/concept/abc.py
edf_fusion/concept/analysis.py
edf_fusion/concept/analyzer.py
edf_fusion/concept/auth_info.py
edf_fusion/concept/case.py
edf_fusion/concept/constant.py
edf_fusion/concept/event.py
edf_fusion/concept/identity.py
edf_fusion/concept/info.py
edf_fusion/concept/pdk.py
edf_fusion/helper/__init__.py
edf_fusion/helper/aiohttp.py
edf_fusion/helper/config.py
edf_fusion/helper/datetime.py
edf_fusion/helper/filesystem.py
edf_fusion/helper/logging.py
edf_fusion/helper/notifier.py
edf_fusion/helper/pubsub.py
edf_fusion/helper/redis.py
edf_fusion/helper/serializing.py
edf_fusion/helper/streaming.py
edf_fusion/helper/subprocess.py
edf_fusion/helper/timer.py
edf_fusion/helper/tracing.py
edf_fusion/helper/zip.py
edf_fusion/server/__init__.py
edf_fusion/server/config.py
edf_fusion/server/storage.py
edf_fusion/server/synchronizer.py
edf_fusion/server/auth/__init__.py
edf_fusion/server/auth/config.py
edf_fusion/server/auth/impl.py
edf_fusion/server/auth/backend/__init__.py
edf_fusion/server/auth/backend/abc.py
edf_fusion/server/auth/backend/basic.py
edf_fusion/server/auth/backend/keycloak.py
edf_fusion/server/case/__init__.py
edf_fusion/server/case/config.py
edf_fusion/server/case/context.py
edf_fusion/server/case/impl.py
edf_fusion/server/constant/__init__.py
edf_fusion/server/constant/config.py
edf_fusion/server/constant/impl.py
edf_fusion/server/download/__init__.py
edf_fusion/server/download/config.py
edf_fusion/server/download/impl.py
edf_fusion/server/event/__init__.py
edf_fusion/server/event/config.py
edf_fusion/server/event/impl.py
edf_fusion/server/info/__init__.py
edf_fusion-2.0.0.dist-info/licenses/LICENSE
edf_fusion-2.0.0.dist-info/METADATA
edf_fusion-2.0.0.dist-info/WHEEL
edf_fusion-2.0.0.dist-info/top_level.txt
edf_fusion-2.0.0.dist-info/RECORD
