Metadata-Version: 2.4
Name: edf-fusion
Version: 2.0.0
Summary: Fusion Framework Library
Author-email: CERT-EDF <cert@edf.fr>
License-Expression: MIT
Project-URL: Homepage, https://github.com/cert-edf/fusion
Project-URL: Repository, https://github.com/cert-edf/fusion
Project-URL: Bug Tracker, https://github.com/cert-edf/fusion/issues
Keywords: edf,fusion,framework,library
Classifier: Development Status :: 5 - Production/Stable
Classifier: Intended Audience :: Developers
Classifier: Operating System :: OS Independent
Classifier: Programming Language :: Python :: 3
Classifier: Programming Language :: Python :: 3 :: Only
Classifier: Topic :: Utilities
Classifier: Topic :: Security
Requires-Python: >=3.12
License-File: LICENSE
Requires-Dist: rich~=14.1
Requires-Dist: redis~=7.0
Requires-Dist: pyyaml~=6.0
Requires-Dist: aiofile~=3.9
Requires-Dist: aiohttp~=3.11
Requires-Dist: aiohttp-sse~=2.2
Requires-Dist: aiohttp-session[secure]~=2.12
Provides-Extra: auth-basic
Requires-Dist: argon2-cffi~=23.1; extra == "auth-basic"
Provides-Extra: auth-keycloak
Requires-Dist: python-keycloak~=4.7; extra == "auth-keycloak"
Dynamic: license-file
